pyprogressbars.py
pyprogressbars-0.0.3.dist-info/METADATA
pyprogressbars-0.0.3.dist-info/WHEEL
pyprogressbars-0.0.3.dist-info/top_level.txt
pyprogressbars-0.0.3.dist-info/RECORD
