Metadata-Version: 2.1
Name: pyprogressbars
Version: 0.0.3
Summary: A minimalistic progress indicators library for usage in CLI based python projects
Home-page: https://github.com/eckarthik/pyprogressbars
Author: Karthik E C
Author-email: eckarthik39@gmail.com
Classifier: Programming Language :: Python :: 3
Classifier: License :: OSI Approved :: MIT License
Classifier: Operating System :: OS Independent
Requires-Python: >=3.0
